[
    {
        "category": "Technology",
        "percentage": 30
    },
    {
        "category": "Computer Hardware",
        "percentage": 70
    },
    {
        "category": "Electronics",
        "percentage": 40
    },
    {
        "category": "Information",
        "percentage": 20
    },
    {
        "category": "Internet",
        "percentage": 10
    },
    {
        "category": "Science",
        "percentage": 10
    },
    {
        "category": "Engineering",
        "percentage": 20
    }
]